incrdecrlib/__init__.py
incrdecrlib/incrdecrnum.py
incrdecrlib-0.1.dist-info/METADATA
incrdecrlib-0.1.dist-info/WHEEL
incrdecrlib-0.1.dist-info/top_level.txt
incrdecrlib-0.1.dist-info/RECORD
